squatter/__init__.py
squatter/__main__.py
squatter/__version__.py
squatter/templates.py
squatter/tests/__init__.py
squatter/tests/__main__.py
squatter-1.2.0.dist-info/METADATA
squatter-1.2.0.dist-info/WHEEL
squatter-1.2.0.dist-info/entry_points.txt
squatter-1.2.0.dist-info/licenses/LICENSE
squatter-1.2.0.dist-info/RECORD
