Metadata-Version: 2.4
Name: squatter
Version: 1.2.0
Dynamic: Summary
Project-URL: Home, https://github.com/python-packaging/squatter
Author: Tim Hatch
Author-email: Amethyst Reese <amethyst@n7.gg>
License-Expression: MIT
License-File: LICENSE
Requires-Python: >=3.12
Requires-Dist: click>=8
Requires-Dist: hatch>=1.14
Requires-Dist: twine
Provides-Extra: dev
Requires-Dist: black==25.1.0; extra == 'dev'
Requires-Dist: coverage==7.8.0; extra == 'dev'
Requires-Dist: flake8==7.2.0; extra == 'dev'
Requires-Dist: mypy==1.15.0; extra == 'dev'
Requires-Dist: tox==4.26.0; extra == 'dev'
Requires-Dist: ufmt==2.8.0; extra == 'dev'
Requires-Dist: usort==1.0.8; extra == 'dev'
Requires-Dist: volatile==2.1.0; extra == 'dev'
